pulya/__init__.py
pulya/application.py
pulya/asgi.py
pulya/containers.py
pulya/headers.py
pulya/params.py
pulya/py.typed
pulya/request.py
pulya/responses.py
pulya/routing.py
pulya/rsgi.py
pulya/testing.py
pulya-0.1.0.dist-info/WHEEL
pulya-0.1.0.dist-info/METADATA
pulya-0.1.0.dist-info/RECORD
