Metadata-Version: 2.3
Name: pulya
Version: 0.1.0
Summary: Tiny web framework based on msgspec and dependency-injector
Author: Roman Tolkachyov
Author-email: Roman Tolkachyov <roman@tolkachyov.name>
Requires-Dist: httpx
Requires-Dist: dependency-injector
Requires-Dist: msgspec
Requires-Dist: python-matchit
Requires-Dist: asgiref
Requires-Python: >=3.12
